helper/__init__.py
helper/alerts.py
helper/execute_script.py
helper/file_upload.py
helper/for_test.py
helper/get_attribs.py
helper/lists_dropdown.py
helper/redirect.py
helper/scroll.py
helper/selector.py
helper/selenium2.py
helper/waiting.py
pyselpom/__init__.py
pyselpom/conftest_example.py
pyselpom/main.py
pyselpom/windows_handlers.py
pyselpom-1.2.3.dist-info/METADATA
pyselpom-1.2.3.dist-info/WHEEL
pyselpom-1.2.3.dist-info/top_level.txt
pyselpom-1.2.3.dist-info/RECORD
