Metadata-Version: 2.1
Name: pyselpom
Version: 1.2.3
Summary: PySelPOM is a Page Object Model selenium based framework for humans.
Home-page: https://github.com/c-pher/PySelenPOM
Author: Andrey Komissarov
Author-email: a.komisssarov@gmail.com
License: GNU General Public License v3.0
Platform: UNKNOWN
Classifier: Programming Language :: Python :: 3
Classifier: License :: OSI Approved :: GNU General Public License v3 (GPLv3)
Classifier: Operating System :: OS Independent
Requires-Python: >=3.9
Requires-Dist: selenium (>=4.1.0)
Requires-Dist: plogger (==1.0.3)
